LICENSE
macro_counter/__init__.py
macro_counter/adapters/__init__.py
macro_counter/adapters/file.py
macro_counter/adapters/mongo.py
macro_counter/app/__init__.py
macro_counter/app/parsers.py
macro_counter/app/prompt.py
macro_counter/core/__init__.py
macro_counter/core/settings.py
macro_counter/exceptions.py
macro_counter/fields.py
macro_counter/models.py
macro_counter/repositories/components/__init__.py
macro_counter/repositories/components/abstract.py
macro_counter/repositories/components/local.py
macro_counter/repositories/components/mongo.py
macro_counter/utils.py
macro_counter-0.2.2.dist-info/entry_points.txt
macro_counter-0.2.2.dist-info/LICENSE
macro_counter-0.2.2.dist-info/WHEEL
macro_counter-0.2.2.dist-info/METADATA
macro_counter-0.2.2.dist-info/RECORD
