Metadata-Version: 2.1
Name: macro-counter
Version: 0.2.2
Summary: Python macro nutrient counter.
Home-page: https://github.com/ludwig778/macro_counter
License: GPLv3
Author: Laurent Arthur
Author-email: laurent.arthur75@gmail.com
Requires-Python: >=3.8,<4.0
Classifier: License :: OSI Approved :: GNU General Public License v3 (GPLv3)
Classifier: License :: Other/Proprietary License
Classifier: Operating System :: MacOS :: MacOS X
Classifier: Operating System :: POSIX :: Linux
Classifier: Programming Language :: Python
Classifier: Programming Language :: Python :: 3
Classifier: Programming Language :: Python :: 3.10
Classifier: Programming Language :: Python :: 3.8
Classifier: Programming Language :: Python :: 3.9
Requires-Dist: dnspython (>=2.1.0,<3.0.0)
Requires-Dist: prompt-toolkit (>=3.0.18,<4.0.0)
Requires-Dist: pydantic (>=1.9.0,<2.0.0)
Requires-Dist: pymongo (>=3.11.4,<4.0.0)
Requires-Dist: pyparsing (>=2.4.7,<3.0.0)
Requires-Dist: tabulate (>=0.8.9,<0.9.0)
Project-URL: Repository, https://github.com/ludwig778/macro_counter
